06_fifo/verilog/fifo_8_8_syn.v
//同步fifo设计
`timescale  1ns / 100ps
module fifo_8_8_syn (
  wr,
  rd,
  rst_n,
  clk,
  full,
  empty,
  full_err,
  empty_err,
  datain,
  dataout
);
  `define       DEPTH         16   //fifo_mem深度
  `define       WIDTH         8    //fifo_mem位宽
  `define       BSIZE         4    //地址线位宽

  input                 wr;     //fifo写使能,高有效
  input                 rd;     //fifo读使能,高有效
  input                 rst_n;  //fifo全局复位
  input                 clk;    //同步fifo时钟
  output                full;   //fifo存储空间满
  output                empty;  //fifo存储空间空
  output                full_err; //fifo写错误
  output                empty_err; //fifo读错误
  input   [`WIDTH-1:0]  datain; //fifo输入
  output  [`WIDTH-1:0]  dataout;//fifo输出

   
  //计算fifo_mem的已用空间,并产生读写fifo_mem地址
  reg     [`BSIZE:0]    cnt;        //用于计算已存储空间
  reg     [`BSIZE-1:0]  wr_addr;    //写fifo_mem的地址
  reg     [`BSIZE-1:0]  rd_addr;    //读fifo_mem的地址
  always @ ( posedge clk or negedge rst_n ) begin
    if ( ~rst_n ) begin
      cnt     <= #1 5'b0_0000;
      wr_addr <= #1 4'b0000;
      rd_addr <= #1 4'b0000;
    end
    else if ( wr && cnt != `DEPTH ) begin   //写入fifo,且未存满`DEPTH个数据
      cnt     <= #1 cnt + 5'b0_0001;        //计数器cnt +1
      wr_addr <= #1 wr_addr + 4'b0001;      //写fifo_addr +1
      rd_addr <= #1 rd_addr;                //读fifo_addr 不变
    end
    else if ( rd && cnt != 0    ) begin     //读取fifo,且fifo_mem不为空
      cnt     <= #1 cnt - 5'b0_0001;        //计数器cnt -1
      wr_addr <= #1 wr_addr;                //写fifo_addr 不变
      rd_addr <= #1 rd_addr + 4'b0001;      //读fifo_addr +1
    end
    else begin
      cnt     <= #1 cnt;
      wr_addr <= #1 wr_addr;
      rd_addr <= #1 rd_addr;
    end
  end

  //fifo write 
  reg   [`WIDTH-1:0]   fifo_mem  [0:`DEPTH-1];  
  always @ ( posedge clk or negedge rst_n ) begin
    if ( ~rst_n ) begin
      $readmemb ( "fifo_mem_rst.txt", fifo_mem );
    end
    else if ( wr && cnt != `DEPTH ) begin
      fifo_mem[wr_addr] <= #1 datain;
    end
    else begin
      fifo_mem[wr_addr] <= #1 fifo_mem[wr_addr];
    end
  end
  //fifo write control-full
  wire           full;
  assign  full  = cnt[`BSIZE];   //cnt为16，empty有效
  //fifo write control-full_err
  reg           full_err;
  always @ ( posedge clk or negedge rst_n ) begin
    if ( ~rst_n ) begin
      full_err    <= #1 1'b0;
    end
    else if ( wr && cnt == `DEPTH) begin
      full_err    <= #1 1'b1;
    end
    else begin
      full_err    <= #1 1'b0;
    end
  end


  //fifo read 
  reg   [`WIDTH-1:0]   dataout;  
  always @ ( posedge clk or negedge rst_n ) begin
    if ( ~rst_n ) begin
      dataout     <= #1 8'bz;
    end
    else if ( rd && cnt != 0    ) begin
      dataout     <= #1 fifo_mem[rd_addr];
    end
    else begin
      dataout     <= #1 8'bz;
    end
  end
  //fifo read control-empty
  wire           empty;
  assign  empty = !(|cnt);  //cnt为0，empty有效
  //fifo read control-empty_err
  reg           empty_err;
  always @ ( posedge clk or negedge rst_n ) begin
    if ( ~rst_n ) begin
      empty_err    <= #1 1'b0;
    end
    else if ( rd && cnt == 5'b0_0000 ) begin
      empty_err    <= #1 1'b1;
    end
    else begin
      empty_err    <= #1 1'b0;
    end
  end

endmodule

06_fifo/verilog/fifo_8_8_syn_tb.v
`timescale  1ns / 100ps
module fifo_8_8_syn_tb ();
  //clk 设置
  reg         clk;
  reg         rst_n;
  reg         wr;
  reg         rd;
  reg   [7:0] datain;

  initial begin
    $dumpfile("fifo_8_8_syn_tb_wave.vcd");
    $dumpvars;
  end


  task delay; //用于延迟 number个clk周期
    input [31:0]  number;
    begin
        repeat ( number ) @ ( posedge clk );
        #5;
    end
  endtask

  //clk设置
  initial begin
    clk       = 1'b0; 
  end
  always #10  clk = ~clk;

  //其他信号设置
  initial begin
    rst_n     = 1'b1;
    wr        = 1'b0;
    rd        = 1'b0;
    datain    = 8'b0;
    //1.全局复位
    delay(1);  rst_n = 1'b0;
    delay(1);
    rst_n     = 1'b1;
    //2.写使能，并输入数据，多写两个
    delay(1);
    wr        = 1'b1;
    while ( datain < 18 ) begin
      datain  = datain + 8'h01;
      delay(1);
    end
    wr        = 1'b0;
    //3.读使能，多读两个无效位来测试empty
    delay(2);
    rd        = 1'b1;
    delay(18);
    rd        = 1'b0;
    //4.finish
    delay(2);
    $finish;
  end
  
  wire        full;
  wire        full_err;
  wire        empty;
  wire        empty_err;
  wire  [7:0] dataout;

  fifo_8_8_syn fifo_duf (
    .wr       ( wr ),
    .rd       ( rd ),
    .rst_n    ( rst_n ),
    .clk      ( clk ),
    .full     ( full ),
    .empty    ( empty ),
    .full_err ( full_err ),
    .empty_err( empty_err ),
    .datain   ( datain ),
    .dataout  ( dataout )
  );

endmodule

06_fifo/modelsim_sim/fifo_tb_dly_wave.vcd
$date
	Sun Aug 23 15:01:44 2020
$end
$version
	ModelSim Version 10.4
$end
$timescale
	100ps
$end

$scope module fifo_8_8_syn_tb $end
$var reg 1 ! clk $end
$var reg 1 " rst_n $end
$var reg 1 # wr $end
$var reg 1 $ rd $end
$var reg 8 % datain [7:0] $end
$var wire 1 & full $end
$var wire 1 ' full_err $end
$var wire 1 ( empty $end
$var wire 1 ) empty_err $end
$var wire 1 * dataout [7] $end
$var wire 1 + dataout [6] $end
$var wire 1 , dataout [5] $end
$var wire 1 - dataout [4] $end
$var wire 1 . dataout [3] $end
$var wire 1 / dataout [2] $end
$var wire 1 0 dataout [1] $end
$var wire 1 1 dataout [0] $end

$scope task delay $end
$var reg 32 2 number [31:0] $end
$upscope $end

$scope module fifo_duf $end
$var wire 1 3 wr $end
$var wire 1 4 rd $end
$var wire 1 5 rst_n $end
$var wire 1 6 clk $end
$var wire 1 & full $end
$var wire 1 ( empty $end
$var reg 1 7 full_err $end
$var reg 1 8 empty_err $end
$var wire 1 9 datain [7] $end
$var wire 1 : datain [6] $end
$var wire 1 ; datain [5] $end
$var wire 1 < datain [4] $end
$var wire 1 = datain [3] $end
$var wire 1 > datain [2] $end
$var wire 1 ? datain [1] $end
$var wire 1 @ datain [0] $end
$var reg 8 A dataout [7:0] $end
$var reg 5 B cnt [4:0] $end
$var reg 4 C wr_addr [3:0] $end
$var reg 4 D rd_addr [3:0] $end
$upscope $end
$upscope $end
$enddefinitions $end
#0
$dumpvars
0!
1"
0#
0$
b0 %
bx 2
x7
x8
bx A
bx B
bx C
bx D
x&
x'
x(
x)
x1
x0
x/
x.
x-
x,
x+
x*
0@
0?
0>
0=
0<
0;
0:
09
06
15
04
03
$end
#10
0"
b1 2
05
#20
b0 B
b0 C
b0 D
07
bz A
08
0&
1(
0'
z1
z0
z/
z.
z-
z,
z+
z*
0)
#100
1!
16
#150
1"
15
#200
0!
06
#300
1!
16
#350
1#
b1 %
13
1@
#400
0!
06
#500
1!
16
#510
b1 B
b1 C
0(
#550
b10 %
0@
1?
#600
0!
06
#700
1!
16
#710
b10 B
b10 C
#750
b11 %
1@
#800
0!
06
#900
1!
16
#910
b11 B
b11 C
#950
b100 %
0@
0?
1>
#1000
0!
06
#1100
1!
16
#1110
b100 B
b100 C
#1150
b101 %
1@
#1200
0!
06
#1300
1!
16
#1310
b101 B
b101 C
#1350
b110 %
0@
1?
#1400
0!
06
#1500
1!
16
#1510
b110 B
b110 C
#1550
b111 %
1@
#1600
0!
06
#1700
1!
16
#1710
b111 B
b111 C
#1750
b1000 %
0@
0?
0>
1=
#1800
0!
06
#1900
1!
16
#1910
b1000 B
b1000 C
#1950
b1001 %
1@
#2000
0!
06
#2100
1!
16
#2110
b1001 B
b1001 C
#2150
b1010 %
0@
1?
#2200
0!
06
#2300
1!
16
#2310
b1010 B
b1010 C
#2350
b1011 %
1@
#2400
0!
06
#2500
1!
16
#2510
b1011 B
b1011 C
#2550
b1100 %
0@
0?
1>
#2600
0!
06
#2700
1!
16
#2710
b1100 B
b1100 C
#2750
b1101 %
1@
#2800
0!
06
#2900
1!
16
#2910
b1101 B
b1101 C
#2950
b1110 %
0@
1?
#3000
0!
06
#3100
1!
16
#3110
b1110 B
b1110 C
#3150
b1111 %
1@
#3200
0!
06
#3300
1!
16
#3310
b1111 B
b1111 C
#3350
b10000 %
0@
0?
0>
0=
1<
#3400
0!
06
#3500
1!
16
#3510
b10000 B
b0 C
1&
#3550
b10001 %
1@
#3600
0!
06
#3700
1!
16
#3710
17
1'
#3750
b10010 %
0@
1?
#3800
0!
06
#3900
1!
16
#3950
0#
b10 2
03
#4000
0!
06
#4100
1!
16
#4110
07
0'
#4200
0!
06
#4300
1!
16
#4350
1$
b10010 2
14
#4400
0!
06
#4500
1!
16
#4510
b1111 B
b1 D
b1 A
0&
11
00
0/
0.
0-
0,
0+
0*
#4600
0!
06
#4700
1!
16
#4710
b1110 B
b10 D
b10 A
01
10
#4800
0!
06
#4900
1!
16
#4910
b1101 B
b11 D
b11 A
11
#5000
0!
06
#5100
1!
16
#5110
b1100 B
b100 D
b100 A
01
00
1/
#5200
0!
06
#5300
1!
16
#5310
b1011 B
b101 D
b101 A
11
#5400
0!
06
#5500
1!
16
#5510
b1010 B
b110 D
b110 A
01
10
#5600
0!
06
#5700
1!
16
#5710
b1001 B
b111 D
b111 A
11
#5800
0!
06
#5900
1!
16
#5910
b1000 B
b1000 D
b1000 A
01
00
0/
1.
#6000
0!
06
#6100
1!
16
#6110
b111 B
b1001 D
b1001 A
11
#6200
0!
06
#6300
1!
16
#6310
b110 B
b1010 D
b1010 A
01
10
#6400
0!
06
#6500
1!
16
#6510
b101 B
b1011 D
b1011 A
11
#6600
0!
06
#6700
1!
16
#6710
b100 B
b1100 D
b1100 A
01
00
1/
#6800
0!
06
#6900
1!
16
#6910
b11 B
b1101 D
b1101 A
11
#7000
0!
06
#7100
1!
16
#7110
b10 B
b1110 D
b1110 A
01
10
#7200
0!
06
#7300
1!
16
#7310
b1 B
b1111 D
b1111 A
11
#7400
0!
06
#7500
1!
16
#7510
b0 B
b0 D
b10000 A
1(
01
00
0/
0.
1-
#7600
0!
06
#7700
1!
16
#7710
bz A
18
z1
z0
z/
z.
z-
z,
z+
z*
1)
#7800
0!
06
#7900
1!
16
#7950
0$
b10 2
04
#8000
0!
06
#8100
1!
16
#8110
08
0)
