06_fifo/verilog/fifo_8_8_syn.v
//同步fifo设计
`timescale  1ns / 100ps
module fifo_8_8_syn (
  wr,
  rd,
  rst_n,
  clk,
  full,
  empty,
  full_err,
  empty_err,
  datain,
  dataout,
	cnt
);
  `define       DEPTH         16   //fifo_mem深度
  `define       WIDTH         8    //fifo_mem位宽
  `define       BSIZE         4    //地址线位宽

  input                 wr;     //fifo写使能,高有效
  input                 rd;     //fifo读使能,高有效
  input                 rst_n;  //fifo全局复位
  input                 clk;    //同步fifo时钟
  output                full;   //fifo存储空间满
  output                empty;  //fifo存储空间空
  output                full_err; //fifo写错误
  output                empty_err; //fifo读错误
  input   [`WIDTH-1:0]  datain; //fifo输入
  output  [`WIDTH-1:0]  dataout;//fifo输出
	output	[`BSIZE-1:0]	cnt;

   
  //计算fifo_mem的已用空间,并产生读写fifo_mem地址
  reg     [`BSIZE:0]    cnt;        //用于计算已存储空间
  reg     [`BSIZE-1:0]  wr_addr;    //写fifo_mem的地址
  reg     [`BSIZE-1:0]  rd_addr;    //读fifo_mem的地址
  always @ ( posedge clk or negedge rst_n ) begin
    if ( ~rst_n ) begin
      cnt     <= #1 5'b0_0000;
      wr_addr <= #1 4'b0000;
      rd_addr <= #1 4'b0000;
    end
		//读写同时有效
		else if ( rd && wr ) begin
			if( cnt == 0 ) begin							//空，只写
				cnt     <= #1 cnt + 5'b0_0001;        //计数器cnt +1
				wr_addr <= #1 wr_addr + 4'b0001;      //写fifo_addr +1
				rd_addr <= #1 rd_addr;                //读fifo_addr 不变
			end
			else if ( cnt == `DEPTH ) begin		//满，只读
				cnt     <= #1 cnt - 5'b0_0001;        //计数器cnt -1
				wr_addr <= #1 wr_addr;                //写fifo_addr 不变
				rd_addr <= #1 rd_addr + 4'b0001;      //读fifo_addr +1
			end
			else begin												//非空非满，同时读写
				cnt     <= #1 cnt;
				wr_addr <= #1 wr_addr + 4'b0001;
				rd_addr <= #1 rd_addr	+ 4'b0001;
			end
		end
		//仅写有效
		else if ( ~rd && wr ) begin
			if( cnt != `DEPTH ) begin					//非满，只写，满则保持
				cnt     <= #1 cnt + 5'b0_0001;        //计数器cnt +1
				wr_addr <= #1 wr_addr + 4'b0001;      //写fifo_addr +1
				rd_addr <= #1 rd_addr;                //读fifo_addr 不变
			end
		end
		//仅读有效
		else if ( rd && ~wr ) begin
			if ( cnt != 0 ) begin							//非空，只读，空则保持
				cnt     <= #1 cnt - 5'b0_0001;        //计数器cnt -1
				wr_addr <= #1 wr_addr;                //写fifo_addr 不变
				rd_addr <= #1 rd_addr + 4'b0001;      //读fifo_addr +1
			end
		end
		//读写均无效，不读不写
		else begin
      cnt     <= #1 cnt;
      wr_addr <= #1 wr_addr;
      rd_addr <= #1 rd_addr;
    end
  end

  //fifo write 
  reg   [`WIDTH-1:0]   fifo_mem  [0:`DEPTH-1];  
  always @ ( posedge clk ) begin
    if ( wr && cnt != `DEPTH ) begin
      fifo_mem[wr_addr] <= #1 datain;
    end
    else begin
      fifo_mem[wr_addr] <= #1 fifo_mem[wr_addr];
    end
  end
  //fifo write control-full
  wire           full;
  assign  full  = cnt[`BSIZE];   //cnt为16，empty有效
  //fifo write control-full_err
  reg           full_err;
  always @ ( posedge clk or negedge rst_n ) begin
    if ( ~rst_n ) begin
      full_err    <= #1 1'b0;
    end
    else if ( wr && cnt == `DEPTH) begin
      full_err    <= #1 1'b1;
    end
    else begin
      full_err    <= #1 1'b0;
    end
  end


  //fifo read 
  reg   [`WIDTH-1:0]   dataout;  
  always @ ( posedge clk or negedge rst_n ) begin
    if ( ~rst_n ) begin
      dataout     <= #1 8'b0;
    end
    else if ( rd && cnt != 0    ) begin
      dataout     <= #1 fifo_mem[rd_addr];
    end
    else begin
      dataout     <= #1 dataout;
    end
  end
  //fifo read control-empty
  wire           empty;
  assign  empty = !(|cnt);  //cnt为0，empty有效
  //fifo read control-empty_err
  reg           empty_err;
  always @ ( posedge clk or negedge rst_n ) begin
    if ( ~rst_n ) begin
      empty_err    <= #1 1'b0;
    end
    else if ( rd && cnt == 5'b0_0000 ) begin
      empty_err    <= #1 1'b1;
    end
    else begin
      empty_err    <= #1 1'b0;
    end
  end

endmodule

06_fifo/verilog/fifo_8_8_syn_tb_1.v
`timescale  1ns / 100ps
//fifo上升沿触发，数据等等在下降沿给
module fifo_8_8_syn_tb();
  //clk 设置
  reg         clk;
  reg         rst_n;
  reg         wr;
  reg         rd;
  reg   [7:0] datain;
	
	wire        full;
  wire        full_err;
  wire        empty;
  wire        empty_err;
  wire  [7:0] dataout;
	wire	[4:0]	cnt;

	fifo_8_8_syn fifo_duf (
    .wr       ( wr ),
    .rd       ( rd ),
    .rst_n    ( rst_n ),
    .clk      ( clk ),
    .full     ( full ),
    .empty    ( empty ),
    .full_err ( full_err ),
    .empty_err( empty_err ),
    .datain   ( datain ),
    .dataout  ( dataout ),
		.cnt			( cnt )
  );

  initial begin
    $dumpfile("fifo_8_8_syn_tb_wave.vcd");
    $dumpvars;
  end

  //clk设置
  initial begin
    clk       = 1'b0; 
  end
  always #10  clk = ~clk;
	//Initial input
	initial begin
		datain		= 8'b0;
		rd				= 1'b0;
		wr				= 1'b0;
		//reset fifo
		rst_n			= 1'b1;
		@ (posedge clk);
		rst_n			= 1'b0;
		@ (posedge clk);
		rst_n			= 1'b1;
		//检查复位是否正确
		if	( ~empty ) begin
			$display("\nError at time %0t:", $time);
			$display("After reset, empty status not asserted\n");
			$stop;
		end
		if	( full ) begin
			$display("\nError at time %0t:", $time);
			$display("After reset, full status not asserted\n");
			$stop;
		end
	end
	
	reg					rw_en;				//读写有效
	reg					cycle;				//循环计数，使读数慢于写数
	reg		[7:0]	exp_data;			//读数期望值
	reg					filled_f;			//
	reg					fast_wr;
	reg					fast_rd;
	initial begin
		rw_en			= 1'b0;
		fast_wr		= 1'b1;
		fast_rd		= 1'b0;
		cycle			=	1'b0;
		exp_data	= 8'd0;
		filled_f	= 1'b0;
		repeat(10) @( posedge clk);
		rw_en			= 1'b1;
	end
	always @( negedge clk or negedge rst_n ) begin
    if ( ~rst_n ) begin
      cycle		= 1'b0;
    end
    else begin
      cycle		= cycle + 1'b1;
    end
	end
	//读，下降沿给读使能
	always @ ( negedge clk or negedge rst_n ) begin
		if ( ~rst_n ) begin
			rd				<= 1'b0;
			exp_data	<= 8'b0;
		end
		else if ( rw_en &&  ( fast_rd || cycle ) && ( ~empty )) begin
			rd				<= 1'b1;
			exp_data	<= exp_data + 1;
		end
		else begin
			rd				<= 1'b0;
			exp_data	<= exp_data;
		end
	end
	//读验证,下降沿验证
	always @ ( negedge clk ) begin
		if ( rw_en && rd && ( dataout != exp_data )) begin
			$display("\nError at time %0t:", $time);
			$display("Expect data_out = %h", exp_data);
			$display("Actual data out = %h", dataout);
			$stop;
		end
	end
	
	//写，下降沿给写使能
	always @ ( negedge clk or negedge rst_n ) begin
		if ( ~rst_n ) begin
			wr			<= 1'b0;
			datain	<= 8'b0;
		end
		else if ( rw_en && ( fast_wr || cycle ) && ( ~full )) begin
			wr			<= 1'b1;
			datain	<= datain + 1'b1;
		end
		else begin
			wr			<= 1'b0;
			datain	<= datain; 
		end
	end

	//仿真完成，下降沿做检测
	always @ ( negedge clk or negedge rst_n ) begin
		if (filled_f && empty ) begin
			$display ("\nSimulation complete --no errors\n");
			$stop;
		end
	end

	//分析cnt
	always @ ( cnt ) begin	
		#5;
		case ( cnt )
			5'b0 : begin
				if(~empty || full ) begin
					$display( "\nERROR at time %0t:", $time );
          $display( "fifo_cnt = %h", cnt );
          $display( "empty = %b", empty);
          $display( "full = %b\n",full);
					$stop;
				end
			end
			5'b1_0000: begin
				if ( empty || ~full) begin
					$display( "\nERROR at time %0t:", $time );
          $display( "fifo_cnt = %h", cnt );
          $display( "empty = %b", empty);
          $display( "full = %b\n",full);
					$stop;
				end
				filled_f		= 1'b1;
				fast_wr			= 1'b0;
				fast_rd			= 1'b1;
			end
			default: begin
				 if ( empty || full ) begin
          $display("\nERROR at time %0t:", $time);
          $display("fifo_count = %h", cnt);
          $display("empty = %b",empty);
          $display("full = %b\n",full);
          // Use $stop for debugging
          $stop;
        end
			end
		endcase

	end
endmodule

06_fifo/modelsim_sim/fifo_8_8_syn_tb_wave.vcd
$date
	Mon Aug 24 11:28:55 2020
$end
$version
	ModelSim Version 10.4
$end
$timescale
	100ps
$end

$scope module fifo_8_8_syn_tb $end
$var reg 1 ! clk $end
$var reg 1 " rst_n $end
$var reg 1 # wr $end
$var reg 1 $ rd $end
$var reg 8 % datain [7:0] $end
$var wire 1 & full $end
$var wire 1 ' full_err $end
$var wire 1 ( empty $end
$var wire 1 ) empty_err $end
$var wire 1 * dataout [7] $end
$var wire 1 + dataout [6] $end
$var wire 1 , dataout [5] $end
$var wire 1 - dataout [4] $end
$var wire 1 . dataout [3] $end
$var wire 1 / dataout [2] $end
$var wire 1 0 dataout [1] $end
$var wire 1 1 dataout [0] $end
$var wire 1 2 cnt [4] $end
$var wire 1 3 cnt [3] $end
$var wire 1 4 cnt [2] $end
$var wire 1 5 cnt [1] $end
$var wire 1 6 cnt [0] $end
$var reg 1 7 rw_en $end
$var reg 1 8 cycle $end
$var reg 8 9 exp_data [7:0] $end
$var reg 1 : filled_f $end
$var reg 1 ; fast_wr $end
$var reg 1 < fast_rd $end

$scope module fifo_duf $end
$var wire 1 = wr $end
$var wire 1 > rd $end
$var wire 1 ? rst_n $end
$var wire 1 @ clk $end
$var wire 1 & full $end
$var wire 1 ( empty $end
$var reg 1 A full_err $end
$var reg 1 B empty_err $end
$var wire 1 C datain [7] $end
$var wire 1 D datain [6] $end
$var wire 1 E datain [5] $end
$var wire 1 F datain [4] $end
$var wire 1 G datain [3] $end
$var wire 1 H datain [2] $end
$var wire 1 I datain [1] $end
$var wire 1 J datain [0] $end
$var reg 8 K dataout [7:0] $end
$var reg 5 L cnt [4:0] $end
$var reg 4 M wr_addr [3:0] $end
$var reg 4 N rd_addr [3:0] $end
$upscope $end
$upscope $end
$enddefinitions $end
#0
$dumpvars
0!
1"
0#
0$
b0 %
xA
xB
bx K
bx L
bx M
bx N
07
18
b0 9
0:
1;
0<
x&
x'
x(
x)
x1
x0
x/
x.
x-
x,
x+
x*
x6
x5
x4
x3
x2
0J
0I
0H
0G
0F
0E
0D
0C
0@
1?
0>
0=
$end
#100
1!
1@
0"
0?
08
#110
0A
0B
b0 L
b0 M
b0 N
b0 K
0&
0'
0)
1(
01
00
0/
0.
0-
0,
0+
0*
06
05
04
03
02
#200
0!
0@
#300
1!
1@
1"
1?
#400
0!
0@
18
#500
1!
1@
#600
0!
0@
08
#700
1!
1@
#800
0!
0@
18
#900
1!
1@
#1000
0!
0@
08
#1100
1!
1@
#1200
0!
0@
18
#1300
1!
1@
#1400
0!
0@
08
#1500
1!
1@
#1600
0!
0@
18
#1700
1!
1@
#1800
0!
0@
08
#1900
1!
1@
17
#2000
0!
0@
18
1#
b1 %
1=
1J
#2100
1!
1@
#2110
b1 L
b1 M
0(
16
#2200
0!
0@
08
b10 %
0J
1I
#2300
1!
1@
#2310
b10 L
b10 M
06
15
#2400
0!
0@
18
1$
b1 9
b11 %
1>
1J
#2500
1!
1@
#2510
b11 M
b1 N
b1 K
11
#2600
0!
0@
08
0$
b100 %
0>
0J
0I
1H
#2700
1!
1@
#2710
b11 L
b100 M
16
#2800
0!
0@
18
1$
b10 9
b101 %
1>
1J
#2900
1!
1@
#2910
b101 M
b10 N
b10 K
01
10
#3000
0!
0@
08
0$
b110 %
0>
0J
1I
#3100
1!
1@
#3110
b100 L
b110 M
06
05
14
#3200
0!
0@
18
1$
b11 9
b111 %
1>
1J
#3300
1!
1@
#3310
b111 M
b11 N
b11 K
11
#3400
0!
0@
08
0$
b1000 %
0>
0J
0I
0H
1G
#3500
1!
1@
#3510
b101 L
b1000 M
16
#3600
0!
0@
18
1$
b100 9
b1001 %
1>
1J
#3700
1!
1@
#3710
b1001 M
b100 N
b100 K
01
00
1/
#3800
0!
0@
08
0$
b1010 %
0>
0J
1I
#3900
1!
1@
#3910
b110 L
b1010 M
06
15
#4000
0!
0@
18
1$
b101 9
b1011 %
1>
1J
#4100
1!
1@
#4110
b1011 M
b101 N
b101 K
11
#4200
0!
0@
08
0$
b1100 %
0>
0J
0I
1H
#4300
1!
1@
#4310
b111 L
b1100 M
16
#4400
0!
0@
18
1$
b110 9
b1101 %
1>
1J
#4500
1!
1@
#4510
b1101 M
b110 N
b110 K
01
10
#4600
0!
0@
08
0$
b1110 %
0>
0J
1I
#4700
1!
1@
#4710
b1000 L
b1110 M
06
05
04
13
#4800
0!
0@
18
1$
b111 9
b1111 %
1>
1J
#4900
1!
1@
#4910
b1111 M
b111 N
b111 K
11
#5000
0!
0@
08
0$
b10000 %
0>
0J
0I
0H
0G
1F
#5100
1!
1@
#5110
b1001 L
b0 M
16
#5200
0!
0@
18
1$
b1000 9
b10001 %
1>
1J
#5300
1!
1@
#5310
b1 M
b1000 N
b1000 K
01
00
0/
1.
#5400
0!
0@
08
0$
b10010 %
0>
0J
1I
#5500
1!
1@
#5510
b1010 L
b10 M
06
15
#5600
0!
0@
18
1$
b1001 9
b10011 %
1>
1J
#5700
1!
1@
#5710
b11 M
b1001 N
b1001 K
11
#5800
0!
0@
08
0$
b10100 %
0>
0J
0I
1H
#5900
1!
1@
#5910
b1011 L
b100 M
16
#6000
0!
0@
18
1$
b1010 9
b10101 %
1>
1J
#6100
1!
1@
#6110
b101 M
b1010 N
b1010 K
01
10
#6200
0!
0@
08
0$
b10110 %
0>
0J
1I
#6300
1!
1@
#6310
b1100 L
b110 M
06
05
14
#6400
0!
0@
18
1$
b1011 9
b10111 %
1>
1J
#6500
1!
1@
#6510
b111 M
b1011 N
b1011 K
11
#6600
0!
0@
08
0$
b11000 %
0>
0J
0I
0H
1G
#6700
1!
1@
#6710
b1101 L
b1000 M
16
#6800
0!
0@
18
1$
b1100 9
b11001 %
1>
1J
#6900
1!
1@
#6910
b1001 M
b1100 N
b1100 K
01
00
1/
#7000
0!
0@
08
0$
b11010 %
0>
0J
1I
#7100
1!
1@
#7110
b1110 L
b1010 M
06
15
#7200
0!
0@
18
1$
b1101 9
b11011 %
1>
1J
#7300
1!
1@
#7310
b1011 M
b1101 N
b1101 K
11
#7400
0!
0@
08
0$
b11100 %
0>
0J
0I
1H
#7500
1!
1@
#7510
b1111 L
b1100 M
16
#7600
0!
0@
18
1$
b1110 9
b11101 %
1>
1J
#7700
1!
1@
#7710
b1101 M
b1110 N
b1110 K
01
10
#7800
0!
0@
08
0$
b11110 %
0>
0J
1I
#7900
1!
1@
#7910
b10000 L
b1110 M
1&
06
05
04
03
12
#7960
1:
0;
1<
#8000
0!
0@
18
1$
b1111 9
0#
1>
0=
#8100
1!
1@
#8110
b1111 L
b1111 N
b1111 K
0&
11
16
15
14
13
02
#8200
0!
0@
08
b10000 9
#8300
1!
1@
#8310
b1110 L
b0 N
b10000 K
01
00
0/
0.
1-
06
#8400
0!
0@
18
b10001 9
1#
b11111 %
1=
1J
#8500
1!
1@
#8510
b1111 M
b1 N
b10001 K
11
#8600
0!
0@
08
b10010 9
0#
0=
#8700
1!
1@
#8710
b1101 L
b10 N
b10010 K
01
10
16
05
#8800
0!
0@
18
b10011 9
1#
b100000 %
1=
0J
0I
0H
0G
0F
1E
#8900
1!
1@
#8910
b0 M
b11 N
b10011 K
11
#9000
0!
0@
08
b10100 9
0#
0=
#9100
1!
1@
#9110
b1100 L
b100 N
b10100 K
01
00
1/
06
#9200
0!
0@
18
b10101 9
1#
b100001 %
1=
1J
#9300
1!
1@
#9310
b1 M
b101 N
b10101 K
11
#9400
0!
0@
08
b10110 9
0#
0=
#9500
1!
1@
#9510
b1011 L
b110 N
b10110 K
01
10
16
15
04
#9600
0!
0@
18
b10111 9
1#
b100010 %
1=
0J
1I
#9700
1!
1@
#9710
b10 M
b111 N
b10111 K
11
#9800
0!
0@
08
b11000 9
0#
0=
#9900
1!
1@
#9910
b1010 L
b1000 N
b11000 K
01
00
0/
1.
06
#10000
0!
0@
18
b11001 9
1#
b100011 %
1=
1J
#10100
1!
1@
#10110
b11 M
b1001 N
b11001 K
11
#10200
0!
0@
08
b11010 9
0#
0=
#10300
1!
1@
#10310
b1001 L
b1010 N
b11010 K
01
10
16
05
#10400
0!
0@
18
b11011 9
1#
b100100 %
1=
0J
0I
1H
#10500
1!
1@
#10510
b100 M
b1011 N
b11011 K
11
#10600
0!
0@
08
b11100 9
0#
0=
#10700
1!
1@
#10710
b1000 L
b1100 N
b11100 K
01
00
1/
06
#10800
0!
0@
18
b11101 9
1#
b100101 %
1=
1J
#10900
1!
1@
#10910
b101 M
b1101 N
b11101 K
11
#11000
0!
0@
08
b11110 9
0#
0=
#11100
1!
1@
#11110
b111 L
b1110 N
b11110 K
01
10
16
15
14
03
#11200
0!
0@
18
b11111 9
1#
b100110 %
1=
0J
1I
#11300
1!
1@
#11310
b110 M
b1111 N
b11111 K
11
#11400
0!
0@
08
b100000 9
0#
0=
#11500
1!
1@
#11510
b110 L
b0 N
b100000 K
01
00
0/
0.
0-
1,
06
#11600
0!
0@
18
b100001 9
1#
b100111 %
1=
1J
#11700
1!
1@
#11710
b111 M
b1 N
b100001 K
11
#11800
0!
0@
08
b100010 9
0#
0=
#11900
1!
1@
#11910
b101 L
b10 N
b100010 K
01
10
16
05
#12000
0!
0@
18
b100011 9
1#
b101000 %
1=
0J
0I
0H
1G
#12100
1!
1@
#12110
b1000 M
b11 N
b100011 K
11
#12200
0!
0@
08
b100100 9
0#
0=
#12300
1!
1@
#12310
b100 L
b100 N
b100100 K
01
00
1/
06
#12400
0!
0@
18
b100101 9
1#
b101001 %
1=
1J
#12500
1!
1@
#12510
b1001 M
b101 N
b100101 K
11
#12600
0!
0@
08
b100110 9
0#
0=
#12700
1!
1@
#12710
b11 L
b110 N
b100110 K
01
10
16
15
04
#12800
0!
0@
18
b100111 9
1#
b101010 %
1=
0J
1I
#12900
1!
1@
#12910
b1010 M
b111 N
b100111 K
11
#13000
0!
0@
08
b101000 9
0#
0=
#13100
1!
1@
#13110
b10 L
b1000 N
b101000 K
01
00
0/
1.
06
#13200
0!
0@
18
b101001 9
1#
b101011 %
1=
1J
#13300
1!
1@
#13310
b1011 M
b1001 N
b101001 K
11
#13400
0!
0@
08
b101010 9
0#
0=
#13500
1!
1@
#13510
b1 L
b1010 N
b101010 K
01
10
16
05
#13600
0!
0@
18
b101011 9
1#
b101100 %
1=
0J
0I
1H
#13700
1!
1@
#13710
b1100 M
b1011 N
b101011 K
11
#13800
0!
0@
08
b101100 9
0#
0=
#13900
1!
1@
#13910
b0 L
b1100 N
b101100 K
1(
01
00
1/
06
#14000
0!
0@
18
